djangoldp_hubl_landing/__init__.py
djangoldp_hubl_landing/admin.py
djangoldp_hubl_landing/apps.py
djangoldp_hubl_landing/djangoldp_settings.py
djangoldp_hubl_landing/models.py
djangoldp_hubl_landing/tests.py
djangoldp_hubl_landing/views.py
djangoldp_hubl_landing/migrations/0001_initial.py
djangoldp_hubl_landing/migrations/0002_auto_20211022_1642.py
djangoldp_hubl_landing/migrations/0003_auto_20211022_1737.py
djangoldp_hubl_landing/migrations/0004_remove_clientcontact_name.py
djangoldp_hubl_landing/migrations/0005_auto_20211024_1738.py
djangoldp_hubl_landing/migrations/0006_auto_20211029_0122.py
djangoldp_hubl_landing/migrations/0007_joincontact_phone.py
djangoldp_hubl_landing/migrations/0008_clientcontact_duration.py
djangoldp_hubl_landing/migrations/__init__.py
djangoldp_hubl_landing/templates/client_email.txt
djangoldp_hubl_landing/templates/contact_email_from_client.txt
djangoldp_hubl_landing/templates/contactgeneral_email.txt
djangoldp_hubl_landing/templates/contactgeneralresponse_email.txt
djangoldp_hubl_landing/templates/contactjoin_email.txt
djangoldp_hubl_landing/templates/contactjoinresponse_email.txt
djangoldp_hubl_landing-0.0.6.dist-info/METADATA
djangoldp_hubl_landing-0.0.6.dist-info/WHEEL
djangoldp_hubl_landing-0.0.6.dist-info/top_level.txt
djangoldp_hubl_landing-0.0.6.dist-info/RECORD
